server.py
obol_mcp-0.1.1.dist-info/licenses/LICENSE
obol_mcp-0.1.1.dist-info/METADATA
obol_mcp-0.1.1.dist-info/WHEEL
obol_mcp-0.1.1.dist-info/entry_points.txt
obol_mcp-0.1.1.dist-info/top_level.txt
obol_mcp-0.1.1.dist-info/RECORD
