Metadata-Version: 2.4
Name: obol-mcp
Version: 0.1.1
Summary: FastMCP server for Obol DVT cluster troubleshooting and monitoring
Author-email: Obol Network <support@obol.tech>
License: MIT
Project-URL: Homepage, https://github.com/ObolNetwork/obol-mcp
Project-URL: Repository, https://github.com/ObolNetwork/obol-mcp
Project-URL: Documentation, https://github.com/ObolNetwork/obol-mcp#readme
Project-URL: Issues, https://github.com/ObolNetwork/obol-mcp/issues
Keywords: mcp,obol,dvt,ethereum,staking,distributed-validators,fastmcp
Classifier: Development Status :: 4 - Beta
Classifier: Intended Audience :: Developers
Classifier: Topic :: Software Development :: Libraries :: Python Modules
Classifier: Topic :: System :: Monitoring
Classifier: Programming Language :: Python :: 3
Classifier: Programming Language :: Python :: 3.10
Classifier: Programming Language :: Python :: 3.11
Classifier: Programming Language :: Python :: 3.12
Classifier: Programming Language :: Python :: 3.13
Requires-Python: >=3.10
License-File: LICENSE
Requires-Dist: fastmcp>=2.11.3
Requires-Dist: httpx>=0.27.0
Provides-Extra: dev
Requires-Dist: pytest>=8.0.0; extra == "dev"
Requires-Dist: pytest-asyncio>=0.23.0; extra == "dev"
Requires-Dist: pytest-cov>=4.1.0; extra == "dev"
Requires-Dist: inline-snapshot>=0.13.0; extra == "dev"
Dynamic: license-file
